regular/cli.py
rgpython-1.0.0.dist-info/LICENSE
rgpython-1.0.0.dist-info/METADATA
rgpython-1.0.0.dist-info/WHEEL
rgpython-1.0.0.dist-info/entry_points.txt
rgpython-1.0.0.dist-info/top_level.txt
rgpython-1.0.0.dist-info/RECORD
