Metadata-Version: 2.1
Name: rgpython
Version: 1.0.0
Summary: A Python package to simplify daily use python code.
Home-page: https://github.com/Kamleshgupta1/rgpython
Author: Kamlesh Gupta
Author-email: kamleshguptaom@gmail.com
License: MIT
Platform: UNKNOWN
Classifier: License :: OSI Approved :: MIT License
Classifier: Programming Language :: Python :: 2.7
Classifier: Programming Language :: Python :: 3.4
